virusshare
