Metadata-Version: 2.1
Name: PyVirusShare
Version: 1.0.3
Summary: A Python library/command line to interact with VirusShare API v2.
Home-page: https://github.com/chrsow/PyVirusShare
License: MIT
Platform: UNKNOWN
Classifier: Programming Language :: Python :: 3
Classifier: Operating System :: OS Independent
Classifier: Intended Audience :: Developers
Classifier: License :: OSI Approved :: MIT License
Requires-Python: >=3.6.0
